Workbook

Sheet Quote Bank
A1: ID | B1: Customer's own words | C1: Words | D1: Brand / SKU | E1: Source | F1: Provenance | G1: Emotion | H1: Job to be done | I1: Objection or Benefit | J1: Trigger moment | K1: Time/place | L1: Physical | M1: Former self | N1: Admission | O1: Plain | P1: <12 words | Q1: Marker score | R1: Verdict | S1: Angle
A2: Q001 | B2: After researching the ingredients and company behind this supplement I feel confident taking it. | C2: =IF(LEN(TRIM(B2))=0,0,LEN(TRIM(B2))-LEN(SUBSTITUTE(TRIM(B2)," ",""))+1) | D2: ProHealth NMN Pro (Uthever) | E2: Mark B · 4★ · Jul 2026 · Vine | F2: Verbatim | G2: Pride | H2: Be the person who did the research | I2: BENEFIT · Credentialed brand | J2: Pre-purchase research | O2: Y | P2: =IF(C2<12,"Y","") | Q2: =COUNTIF(K2:P2,"Y") | R2: =IF(Q2>=3,"USE","CONTEXT") | S2: A7 Honest science
A3: Q002 | B3: I also looked at the broader science to see if NMN is just hype. | C3: =IF(LEN(TRIM(B3))=0,0,LEN(TRIM(B3))-LEN(SUBSTITUTE(TRIM(B3)," ",""))+1) | D3: ProHealth NMN Pro (Uthever) | E3: Mark B · 4★ · Jul 2026 · Vine | F3: Verbatim | G3: Fear | H3: Verify it's real and safe | I3: OBJECTION · Category is hype | J3: Pre-purchase research | N3: Y | O3: Y | P3: =IF(C3<12,"Y","") | Q3: =COUNTIF(K3:P3,"Y") | R3: =IF(Q3>=3,"USE","CONTEXT") | S3: A7 Honest science
A4: Q003 | B4: The honest answer is that the science is real but still emerging. | C4: =IF(LEN(TRIM(B4))=0,0,LEN(TRIM(B4))-LEN(SUBSTITUTE(TRIM(B4)," ",""))+1) | D4: ProHealth NMN Pro (Uthever) | E4: Mark B · 4★ · Jul 2026 · Vine | F4: Verbatim | G4: Hope | H4: Verify it's real and safe | I4: OBJECTION · Evidence immature | J4: Pre-purchase research | O4: Y | P4: =IF(C4<12,"Y","") | Q4: =COUNTIF(K4:P4,"Y") | R4: =IF(Q4>=3,"USE","CONTEXT") | S4: A7 Honest science
A5: Q004 | B5: It is not snake oil but the anti aging claims are ahead of the evidence. | C5: =IF(LEN(TRIM(B5))=0,0,LEN(TRIM(B5))-LEN(SUBSTITUTE(TRIM(B5)," ",""))+1) | D5: ProHealth NMN Pro (Uthever) | E5: Mark B · 4★ · Jul 2026 · Vine | F5: Verbatim | G5: Fear | H5: Verify it's real and safe | I5: OBJECTION · Marketing overreach | J5: Comparing brands | O5: Y | P5: =IF(C5<12,"Y","") | Q5: =COUNTIF(K5:P5,"Y") | R5: =IF(Q5>=3,"USE","CONTEXT") | S5: A7 Honest science
A6: Q005 | B6: A 2025 meta analysis found no clear benefit for muscle strength or metabolic markers. | C6: =IF(LEN(TRIM(B6))=0,0,LEN(TRIM(B6))-LEN(SUBSTITUTE(TRIM(B6)," ",""))+1) | D6: ProHealth NMN Pro (Uthever) | E6: Mark B · 4★ · Jul 2026 · Vine | F6: Verbatim | G6: Fear | H6: Verify it's real and safe | I6: OBJECTION · Evidence immature | J6: Pre-purchase research | P6: =IF(C6<12,"Y","") | Q6: =COUNTIF(K6:P6,"Y") | R6: =IF(Q6>=3,"USE","CONTEXT") | S6: A7 Honest science
A7: Q006 | B7: The FDA reversed its 2022 ban and now allows NMN as a supplement. | C7: =IF(LEN(TRIM(B7))=0,0,LEN(TRIM(B7))-LEN(SUBSTITUTE(TRIM(B7)," ",""))+1) | D7: ProHealth NMN Pro (Uthever) | E7: Mark B · 4★ · Jul 2026 · Vine | F7: Verbatim | G7: Relief | H7: Verify it's real and safe | I7: OBJECTION · Was NMN banned? | J7: Pre-purchase research | K7: Y | P7: =IF(C7<12,"Y","") | Q7: =COUNTIF(K7:P7,"Y") | R7: =IF(Q7>=3,"USE","CONTEXT") | S7: A7 Honest science
A8: Q007 | B8: Perhaps in another year or two the effectiveness will be demonstrated in clinical testing. | C8: =IF(LEN(TRIM(B8))=0,0,LEN(TRIM(B8))-LEN(SUBSTITUTE(TRIM(B8)," ",""))+1) | D8: ProHealth NMN Pro (Uthever) | E8: Mark B · 4★ · Jul 2026 · Vine | F8: Verbatim | G8: Hope | H8: Know whether it's working | I8: OBJECTION · Evidence immature | J8: Reorder decision | K8: Y | O8: Y | P8: =IF(C8<12,"Y","") | Q8: =COUNTIF(K8:P8,"Y") | R8: =IF(Q8>=3,"USE","CONTEXT") | S8: A7 Honest science
A9: Q008 | B9: The marketing leans on benefits that are still being studied. | C9: =IF(LEN(TRIM(B9))=0,0,LEN(TRIM(B9))-LEN(SUBSTITUTE(TRIM(B9)," ",""))+1) | D9: ProHealth NMN Pro (Uthever) | E9: Mark B · 4★ · Jul 2026 · Vine | F9: Verbatim | G9: Anger | H9: Not get ripped off | I9: OBJECTION · Marketing overreach | J9: Warning others | O9: Y | P9: =IF(C9<12,"Y","") | Q9: =COUNTIF(K9:P9,"Y") | R9: =IF(Q9>=3,"USE","CONTEXT") | S9: A7 Honest science
A10: Q009 | B10: TMG supports methylation which is important because NMN supplementation can deplete methyl groups. | C10: =IF(LEN(TRIM(B10))=0,0,LEN(TRIM(B10))-LEN(SUBSTITUTE(TRIM(B10)," ",""))+1) | D10: ProHealth NMN Pro (Uthever) | E10: Mark B · 4★ · Jul 2026 · Vine | F10: Verbatim | G10: Pride | H10: Be the person who did the research | I10: BENEFIT · Cofactors included | J10: Reading the label | P10: =IF(C10<12,"Y","") | Q10: =COUNTIF(K10:P10,"Y") | R10: =IF(Q10>=3,"USE","CONTEXT") | S10: A6 Retire the shelf
A11: Q010 | B11: Having all three in one bottle is convenient and actually costs less than buying them separately. | C11: =IF(LEN(TRIM(B11))=0,0,LEN(TRIM(B11))-LEN(SUBSTITUTE(TRIM(B11)," ",""))+1) | D11: ProHealth NMN Pro (Uthever) | E11: Mark B · 4★ · Jul 2026 · Vine | F11: Verbatim | G11: Relief | H11: Simplify my routine | I11: BENEFIT · Consolidation | J11: Doing the price math | O11: Y | P11: =IF(C11<12,"Y","") | Q11: =COUNTIF(K11:P11,"Y") | R11: =IF(Q11>=3,"USE","CONTEXT") | S11: A6 Retire the shelf
A12: Q011 | B12: This is a well thought out stack. | C12: =IF(LEN(TRIM(B12))=0,0,LEN(TRIM(B12))-LEN(SUBSTITUTE(TRIM(B12)," ",""))+1) | D12: ProHealth NMN Pro (Uthever) | E12: Mark B · 4★ · Jul 2026 · Vine | F12: Verbatim | G12: Pride | H12: Simplify my routine | I12: BENEFIT · Formula design | J12: Reading the label | O12: Y | P12: =IF(C12<12,"Y","") | Q12: =COUNTIF(K12:P12,"Y") | R12: =IF(Q12>=3,"USE","CONTEXT") | S12: A6 Retire the shelf
A13: Q012 | B13: The capsules are easy to swallow and have no unpleasant taste. | C13: =IF(LEN(TRIM(B13))=0,0,LEN(TRIM(B13))-LEN(SUBSTITUTE(TRIM(B13)," ",""))+1) | D13: ProHealth NMN Pro (Uthever) | E13: Mark B · 4★ · Jul 2026 · Vine | F13: Verbatim | G13: Relief | H13: Protect a sensitive body | I13: BENEFIT · Sensory ease | J13: First dose | L13: Y | O13: Y | P13: =IF(C13<12,"Y","") | Q13: =COUNTIF(K13:P13,"Y") | R13: =IF(Q13>=3,"USE","CONTEXT") | S13: A5 Gentle start
A14: Q013 | B14: I have noticed slight improved energy levels since starting. | C14: =IF(LEN(TRIM(B14))=0,0,LEN(TRIM(B14))-LEN(SUBSTITUTE(TRIM(B14)," ",""))+1) | D14: ProHealth NMN Pro (Uthever) | E14: Mark B · 4★ · Jul 2026 · Vine | F14: Verbatim | G14: Hope | H14: Get my energy back | I14: BENEFIT · Mild energy | J14: Weeks 2–4 | L14: Y | O14: Y | P14: =IF(C14<12,"Y","") | Q14: =COUNTIF(K14:P14,"Y") | R14: =IF(Q14>=3,"USE","CONTEXT") | S14: A1 You won't feel it
A15: Q014 | B15: The 3 pack provides a 6 month supply at about 232 dollars which is premium pricing. | C15: =IF(LEN(TRIM(B15))=0,0,LEN(TRIM(B15))-LEN(SUBSTITUTE(TRIM(B15)," ",""))+1) | D15: ProHealth NMN Pro (Uthever) | E15: Mark B · 4★ · Jul 2026 · Vine | F15: Verbatim | G15: Anger | H15: Justify the ongoing spend | I15: OBJECTION · Cost per day | J15: Doing the price math | O15: Y | P15: =IF(C15<12,"Y","") | Q15: =COUNTIF(K15:P15,"Y") | R15: =IF(Q15>=3,"USE","CONTEXT") | S15: A3 Do the math
A16: Q015 | B16: ProHealth has been around since 1988 and is a BBB A plus rated company. | C16: =IF(LEN(TRIM(B16))=0,0,LEN(TRIM(B16))-LEN(SUBSTITUTE(TRIM(B16)," ",""))+1) | D16: ProHealth NMN Pro (Uthever) | E16: Mark B · 4★ · Jul 2026 · Vine | F16: Verbatim | G16: Relief | H16: Verify it's real and safe | I16: BENEFIT · Track record | J16: Comparing brands | K16: Y | P16: =IF(C16<12,"Y","") | Q16: =COUNTIF(K16:P16,"Y") | R16: =IF(Q16>=3,"USE","CONTEXT") | S16: A2 The receipt
A17: Q016 | B17: I take a lot of supplements and am very focused on metabolically healthy aging as I am approaching 60. | C17: =IF(LEN(TRIM(B17))=0,0,LEN(TRIM(B17))-LEN(SUBSTITUTE(TRIM(B17)," ",""))+1) | D17: ProHealth NMN Pro (Uthever) | E17: kLr · 4★ · Jun 2026 · Vine | F17: Verbatim | G17: Fear | H17: Stay functional as I age | I17: BENEFIT · Identity fit | J17: Pre-purchase research | K17: Y | M17: Y | P17: =IF(C17<12,"Y","") | Q17: =COUNTIF(K17:P17,"Y") | R17: =IF(Q17>=3,"USE","CONTEXT") | S17: A6 Retire the shelf
A18: Q017 | B18: They can add up, so it's important to me that they are not just effective, but a good value proposition and safe. | C18: =IF(LEN(TRIM(B18))=0,0,LEN(TRIM(B18))-LEN(SUBSTITUTE(TRIM(B18)," ",""))+1) | D18: ProHealth NMN Pro (Uthever) | E18: kLr · 4★ · Jun 2026 · Vine | F18: Verbatim | G18: Anger | H18: Justify the ongoing spend | I18: OBJECTION · Stack tax | J18: Doing the price math | O18: Y | P18: =IF(C18<12,"Y","") | Q18: =COUNTIF(K18:P18,"Y") | R18: =IF(Q18>=3,"USE","CONTEXT") | S18: A3 Do the math
A19: Q018 | B19: It's often hard to quantify changes in the short term on an individual basis. | C19: =IF(LEN(TRIM(B19))=0,0,LEN(TRIM(B19))-LEN(SUBSTITUTE(TRIM(B19)," ",""))+1) | D19: ProHealth NMN Pro (Uthever) | E19: kLr · 4★ · Jun 2026 · Vine | F19: Verbatim | G19: Hope | H19: Know whether it's working | I19: OBJECTION · No feedback loop | J19: Weeks 2–4 | N19: Y | O19: Y | P19: =IF(C19<12,"Y","") | Q19: =COUNTIF(K19:P19,"Y") | R19: =IF(Q19>=3,"USE","CONTEXT") | S19: A1 You won't feel it
A20: Q019 | B20: So many factors come into play in how I may feel on a particular day. | C20: =IF(LEN(TRIM(B20))=0,0,LEN(TRIM(B20))-LEN(SUBSTITUTE(TRIM(B20)," ",""))+1) | D20: ProHealth NMN Pro (Uthever) | E20: kLr · 4★ · Jun 2026 · Vine | F20: Verbatim | G20: Hope | H20: Know whether it's working | I20: OBJECTION · No feedback loop | J20: Weeks 2–4 | L20: Y | N20: Y | O20: Y | P20: =IF(C20<12,"Y","") | Q20: =COUNTIF(K20:P20,"Y") | R20: =IF(Q20>=3,"USE","CONTEXT") | S20: A1 You won't feel it
A21: Q020 | B21: Have I exercised, did I sleep well, am I stressed, did I drink alcohol the day before? | C21: =IF(LEN(TRIM(B21))=0,0,LEN(TRIM(B21))-LEN(SUBSTITUTE(TRIM(B21)," ",""))+1) | D21: ProHealth NMN Pro (Uthever) | E21: kLr · 4★ · Jun 2026 · Vine | F21: Verbatim | G21: Shame | H21: Know whether it's working | I21: OBJECTION · No feedback loop | J21: Weeks 2–4 | L21: Y | N21: Y | O21: Y | P21: =IF(C21<12,"Y","") | Q21: =COUNTIF(K21:P21,"Y") | R21: =IF(Q21>=3,"USE","CONTEXT") | S21: A1 You won't feel it
A22: Q021 | B22: I consider this a long-term health optimizer. | C22: =IF(LEN(TRIM(B22))=0,0,LEN(TRIM(B22))-LEN(SUBSTITUTE(TRIM(B22)," ",""))+1) | D22: ProHealth NMN Pro (Uthever) | E22: kLr · 4★ · Jun 2026 · Vine | F22: Verbatim | G22: Hope | H22: Stay functional as I age | I22: BENEFIT · Insurance frame | J22: Reorder decision | O22: Y | P22: =IF(C22<12,"Y","") | Q22: =COUNTIF(K22:P22,"Y") | R22: =IF(Q22>=3,"USE","CONTEXT") | S22: A1 You won't feel it
A23: Q022 | B23: I am very interested in giving my body the resources it needs to have the best outcome it can have as I age. | C23: =IF(LEN(TRIM(B23))=0,0,LEN(TRIM(B23))-LEN(SUBSTITUTE(TRIM(B23)," ",""))+1) | D23: ProHealth NMN Pro (Uthever) | E23: kLr · 4★ · Jun 2026 · Vine | F23: Verbatim | G23: Hope | H23: Stay functional as I age | I23: BENEFIT · Insurance frame | J23: Reorder decision | L23: Y | O23: Y | P23: =IF(C23<12,"Y","") | Q23: =COUNTIF(K23:P23,"Y") | R23: =IF(Q23>=3,"USE","CONTEXT") | S23: A1 You won't feel it
A24: Q023 | B24: I am not new to these. | C24: =IF(LEN(TRIM(B24))=0,0,LEN(TRIM(B24))-LEN(SUBSTITUTE(TRIM(B24)," ",""))+1) | D24: ProHealth NMN Pro (Uthever) | E24: kLr · 4★ · Jun 2026 · Vine | F24: Verbatim | G24: Pride | H24: Be the person who did the research | I24: BENEFIT · Self-image | J24: Comparing brands | M24: Y | O24: Y | P24: =IF(C24<12,"Y","") | Q24: =COUNTIF(K24:P24,"Y") | R24: =IF(Q24>=3,"USE","CONTEXT") | S24: A4 Dose is the product
A25: Q024 | B25: One might alternate both forms to get some of these benefits without totally breaking the budget. | C25: =IF(LEN(TRIM(B25))=0,0,LEN(TRIM(B25))-LEN(SUBSTITUTE(TRIM(B25)," ",""))+1) | D25: ProHealth NMN Pro (Uthever) | E25: kLr · 4★ · Jun 2026 · Vine | F25: Verbatim | G25: Shame | H25: Justify the ongoing spend | I25: OBJECTION · Cost per day | J25: Doing the price math | N25: Y | O25: Y | P25: =IF(C25<12,"Y","") | Q25: =COUNTIF(K25:P25,"Y") | R25: =IF(Q25>=3,"USE","CONTEXT") | S25: A3 Do the math
A26: Q025 | B26: Lot tested, with public batch-specific certificates. | C26: =IF(LEN(TRIM(B26))=0,0,LEN(TRIM(B26))-LEN(SUBSTITUTE(TRIM(B26)," ",""))+1) | D26: ProHealth NMN Pro (Uthever) | E26: kLr · 4★ · Jun 2026 · Vine | F26: Verbatim | G26: Relief | H26: Verify it's real and safe | I26: BENEFIT · Batch COA | J26: Pre-purchase research | P26: =IF(C26<12,"Y","") | Q26: =COUNTIF(K26:P26,"Y") | R26: =IF(Q26>=3,"USE","CONTEXT") | S26: A2 The receipt
A27: Q026 | B27: Lot number and Best By date is printed on the bottle. | C27: =IF(LEN(TRIM(B27))=0,0,LEN(TRIM(B27))-LEN(SUBSTITUTE(TRIM(B27)," ",""))+1) | D27: ProHealth NMN Pro (Uthever) | E27: kLr · 4★ · Jun 2026 · Vine | F27: Verbatim | G27: Relief | H27: Verify it's real and safe | I27: BENEFIT · Expiry printed | J27: Unboxing / first inspection | O27: Y | P27: =IF(C27<12,"Y","") | Q27: =COUNTIF(K27:P27,"Y") | R27: =IF(Q27>=3,"USE","CONTEXT") | S27: A2 The receipt
A28: Q027 | B28: It is confirmed made at a cGMP third-party certified facility. | C28: =IF(LEN(TRIM(B28))=0,0,LEN(TRIM(B28))-LEN(SUBSTITUTE(TRIM(B28)," ",""))+1) | D28: ProHealth NMN Pro (Uthever) | E28: kLr · 4★ · Jun 2026 · Vine | F28: Verbatim | G28: Relief | H28: Verify it's real and safe | I28: BENEFIT · Manufacturing | J28: Pre-purchase research | P28: =IF(C28<12,"Y","") | Q28: =COUNTIF(K28:P28,"Y") | R28: =IF(Q28>=3,"USE","CONTEXT") | S28: A2 The receipt
A29: Q028 | B29: 300 mg a day for 60 days in 66 adults, a 38% NAD+ increase by day 60. | C29: =IF(LEN(TRIM(B29))=0,0,LEN(TRIM(B29))-LEN(SUBSTITUTE(TRIM(B29)," ",""))+1) | D29: ProHealth NMN Pro (Uthever) | E29: kLr · 4★ · Jun 2026 · Vine | F29: Verbatim | G29: Pride | H29: Be the person who did the research | I29: BENEFIT · Human RCT | J29: Reading the label | K29: Y | P29: =IF(C29<12,"Y","") | Q29: =COUNTIF(K29:P29,"Y") | R29: =IF(Q29>=3,"USE","CONTEXT") | S29: A4 Dose is the product
A30: Q029 | B30: Results vary by interpretation, dose and duration. | C30: =IF(LEN(TRIM(B30))=0,0,LEN(TRIM(B30))-LEN(SUBSTITUTE(TRIM(B30)," ",""))+1) | D30: ProHealth NMN Pro (Uthever) | E30: kLr · 4★ · Jun 2026 · Vine | F30: Verbatim | G30: Fear | H30: Know whether it's working | I30: OBJECTION · Evidence immature | J30: Pre-purchase research | O30: Y | P30: =IF(C30<12,"Y","") | Q30: =COUNTIF(K30:P30,"Y") | R30: =IF(Q30>=3,"USE","CONTEXT") | S30: A7 Honest science
A31: Q030 | B31: Liposomal delivery is supposed to enhance absorption. | C31: =IF(LEN(TRIM(B31))=0,0,LEN(TRIM(B31))-LEN(SUBSTITUTE(TRIM(B31)," ",""))+1) | D31: ProHealth NMN Pro (Uthever) | E31: kLr · 4★ · Jun 2026 · Vine | F31: Verbatim | G31: Hope | H31: Verify it's real and safe | I31: OBJECTION · Absorption claim | J31: Reading the label | P31: =IF(C31<12,"Y","") | Q31: =COUNTIF(K31:P31,"Y") | R31: =IF(Q31>=3,"USE","CONTEXT") | S31: A4 Dose is the product
A32: Q031 | B32: Depending on how much you wish to take, one bottle could last weeks or months. | C32: =IF(LEN(TRIM(B32))=0,0,LEN(TRIM(B32))-LEN(SUBSTITUTE(TRIM(B32)," ",""))+1) | D32: ProHealth NMN Pro (Uthever) | E32: kLr · 4★ · Jun 2026 · Vine | F32: Verbatim | G32: Fear | H32: Justify the ongoing spend | I32: OBJECTION · True supply length | J32: Doing the price math | O32: Y | P32: =IF(C32<12,"Y","") | Q32: =COUNTIF(K32:P32,"Y") | R32: =IF(Q32>=3,"USE","CONTEXT") | S32: A3 Do the math
A33: Q032 | B33: I kind of had high hopes for this longevity supplement. | C33: =IF(LEN(TRIM(B33))=0,0,LEN(TRIM(B33))-LEN(SUBSTITUTE(TRIM(B33)," ",""))+1) | D33: ProHealth NMN Pro (Uthever) | E33: Nancy Taylor · 3★ · Jul 2026 | F33: Verbatim | G33: Grief | H33: Know whether it's working | I33: OBJECTION · Unmet expectation | J33: Weeks 2–4 | N33: Y | O33: Y | P33: =IF(C33<12,"Y","") | Q33: =COUNTIF(K33:P33,"Y") | R33: =IF(Q33>=3,"USE","CONTEXT") | S33: A1 You won't feel it
A34: Q033 | B34: I'm not feeling any different energy wise. | C34: =IF(LEN(TRIM(B34))=0,0,LEN(TRIM(B34))-LEN(SUBSTITUTE(TRIM(B34)," ",""))+1) | D34: ProHealth NMN Pro (Uthever) | E34: Nancy Taylor · 3★ · Jul 2026 | F34: Verbatim | G34: Grief | H34: Get my energy back | I34: OBJECTION · Felt nothing | J34: Weeks 2–4 | L34: Y | O34: Y | P34: =IF(C34<12,"Y","") | Q34: =COUNTIF(K34:P34,"Y") | R34: =IF(Q34>=3,"USE","CONTEXT") | S34: A1 You won't feel it
A35: Q034 | B35: But maybe I need to give it more time? | C35: =IF(LEN(TRIM(B35))=0,0,LEN(TRIM(B35))-LEN(SUBSTITUTE(TRIM(B35)," ",""))+1) | D35: ProHealth NMN Pro (Uthever) | E35: Nancy Taylor · 3★ · Jul 2026 | F35: Verbatim | G35: Hope | H35: Know whether it's working | I35: OBJECTION · Timeline unclear | J35: Weeks 2–4 | N35: Y | O35: Y | P35: =IF(C35<12,"Y","") | Q35: =COUNTIF(K35:P35,"Y") | R35: =IF(Q35>=3,"USE","CONTEXT") | S35: A1 You won't feel it
A36: Q035 | B36: It's not inexpensive so I probably won't be ordering again. | C36: =IF(LEN(TRIM(B36))=0,0,LEN(TRIM(B36))-LEN(SUBSTITUTE(TRIM(B36)," ",""))+1) | D36: ProHealth NMN Pro (Uthever) | E36: Nancy Taylor · 3★ · Jul 2026 | F36: Verbatim | G36: Anger | H36: Justify the ongoing spend | I36: OBJECTION · Cost per day | J36: Reorder decision | O36: Y | P36: =IF(C36<12,"Y","") | Q36: =COUNTIF(K36:P36,"Y") | R36: =IF(Q36>=3,"USE","CONTEXT") | S36: A3 Do the math
A37: Q036 | B37: Was hoping to notice a change while taking. | C37: =IF(LEN(TRIM(B37))=0,0,LEN(TRIM(B37))-LEN(SUBSTITUTE(TRIM(B37)," ",""))+1) | D37: ProHealth NMN Pro (Uthever) | E37: Nancy Taylor · 3★ · Jul 2026 | F37: Verbatim | G37: Grief | H37: Know whether it's working | I37: OBJECTION · Felt nothing | J37: Weeks 2–4 | L37: Y | N37: Y | O37: Y | P37: =IF(C37<12,"Y","") | Q37: =COUNTIF(K37:P37,"Y") | R37: =IF(Q37>=3,"USE","CONTEXT") | S37: A1 You won't feel it
A38: Q037 | B38: As recommended by the bottle I took two pills around 8am. | C38: =IF(LEN(TRIM(B38))=0,0,LEN(TRIM(B38))-LEN(SUBSTITUTE(TRIM(B38)," ",""))+1) | D38: ProHealth NMN Pro (Uthever) | E38: Matthew B · 1★ · Mar 2022 | F38: Verbatim | G38: Anger | H38: Protect a sensitive body | I38: OBJECTION · Dose guidance | J38: First dose | K38: Y | O38: Y | P38: =IF(C38<12,"Y","") | Q38: =COUNTIF(K38:P38,"Y") | R38: =IF(Q38>=3,"USE","CONTEXT") | S38: A5 Gentle start
A39: Q038 | B39: I was unable to fall asleep until 6am the following morning. | C39: =IF(LEN(TRIM(B39))=0,0,LEN(TRIM(B39))-LEN(SUBSTITUTE(TRIM(B39)," ",""))+1) | D39: ProHealth NMN Pro (Uthever) | E39: Matthew B · 1★ · Mar 2022 | F39: Verbatim | G39: Anger | H39: Sleep through the night | I39: OBJECTION · Insomnia | J39: First dose | K39: Y | L39: Y | O39: Y | P39: =IF(C39<12,"Y","") | Q39: =COUNTIF(K39:P39,"Y") | R39: =IF(Q39>=3,"USE","CONTEXT") | S39: A5 Gentle start
A40: Q039 | B40: I experienced an increase in energy, an increase in heart rate, and anxiousness. | C40: =IF(LEN(TRIM(B40))=0,0,LEN(TRIM(B40))-LEN(SUBSTITUTE(TRIM(B40)," ",""))+1) | D40: ProHealth NMN Pro (Uthever) | E40: Matthew B · 1★ · Mar 2022 | F40: Verbatim | G40: Fear | H40: Protect a sensitive body | I40: OBJECTION · Over-stimulation | J40: First dose | L40: Y | O40: Y | P40: =IF(C40<12,"Y","") | Q40: =COUNTIF(K40:P40,"Y") | R40: =IF(Q40>=3,"USE","CONTEXT") | S40: A5 Gentle start
A41: Q040 | B41: I do not drink caffeinated drinks as I am sensitive to caffeine. | C41: =IF(LEN(TRIM(B41))=0,0,LEN(TRIM(B41))-LEN(SUBSTITUTE(TRIM(B41)," ",""))+1) | D41: ProHealth NMN Pro (Uthever) | E41: Matthew B · 1★ · Mar 2022 | F41: Verbatim | G41: Fear | H41: Protect a sensitive body | I41: BENEFIT · Segment tell | J41: Pre-purchase research | L41: Y | O41: Y | P41: =IF(C41<12,"Y","") | Q41: =COUNTIF(K41:P41,"Y") | R41: =IF(Q41>=3,"USE","CONTEXT") | S41: A5 Gentle start
A42: Q041 | B42: I suspect this is just a caffeine pill. | C42: =IF(LEN(TRIM(B42))=0,0,LEN(TRIM(B42))-LEN(SUBSTITUTE(TRIM(B42)," ",""))+1) | D42: ProHealth NMN Pro (Uthever) | E42: Matthew B · 1★ · Mar 2022 | F42: Verbatim | G42: Anger | H42: Not get ripped off | I42: OBJECTION · Is it real? | J42: Abandonment / refund | O42: Y | P42: =IF(C42<12,"Y","") | Q42: =COUNTIF(K42:P42,"Y") | R42: =IF(Q42>=3,"USE","CONTEXT") | S42: A2 The receipt
A43: Q042 | B43: Buyer beware. | C43: =IF(LEN(TRIM(B43))=0,0,LEN(TRIM(B43))-LEN(SUBSTITUTE(TRIM(B43)," ",""))+1) | D43: ProHealth NMN Pro (Uthever) | E43: Matthew B · 1★ · Mar 2022 | F43: Verbatim | G43: Anger | H43: Not get ripped off | I43: OBJECTION · Is it real? | J43: Warning others | O43: Y | P43: =IF(C43<12,"Y","") | Q43: =COUNTIF(K43:P43,"Y") | R43: =IF(Q43>=3,"USE","CONTEXT") | S43: A2 The receipt
A44: Q043 | B44: Will not be taking this again. | C44: =IF(LEN(TRIM(B44))=0,0,LEN(TRIM(B44))-LEN(SUBSTITUTE(TRIM(B44)," ",""))+1) | D44: ProHealth NMN Pro (Uthever) | E44: Matthew B · 1★ · Mar 2022 | F44: Verbatim | G44: Anger | H44: Not get ripped off | I44: OBJECTION · Abandonment | J44: Abandonment / refund | O44: Y | P44: =IF(C44<12,"Y","") | Q44: =COUNTIF(K44:P44,"Y") | R44: =IF(Q44>=3,"USE","CONTEXT") | S44: A5 Gentle start
A45: Q044 | B45: I have bought 12 bottles of this and I have not felt much difference. | C45: =IF(LEN(TRIM(B45))=0,0,LEN(TRIM(B45))-LEN(SUBSTITUTE(TRIM(B45)," ",""))+1) | D45: ProHealth NMN Pro (Uthever) | E45: Rick · 3★ · Sep 2021 | F45: Verbatim | G45: Grief | H45: Know whether it's working | I45: OBJECTION · Felt nothing | J45: Month 2+ | L45: Y | N45: Y | O45: Y | P45: =IF(C45<12,"Y","") | Q45: =COUNTIF(K45:P45,"Y") | R45: =IF(Q45>=3,"USE","CONTEXT") | S45: A1 You won't feel it
A46: Q045 | B46: I don't know where this stuff is stored or how long it's been on the shelves. | C46: =IF(LEN(TRIM(B46))=0,0,LEN(TRIM(B46))-LEN(SUBSTITUTE(TRIM(B46)," ",""))+1) | D46: ProHealth NMN Pro (Uthever) | E46: Rick · 3★ · Sep 2021 | F46: Verbatim | G46: Fear | H46: Verify it's real and safe | I46: OBJECTION · Degradation | J46: Unboxing / first inspection | K46: Y | O46: Y | P46: =IF(C46<12,"Y","") | Q46: =COUNTIF(K46:P46,"Y") | R46: =IF(Q46>=3,"USE","CONTEXT") | S46: A2 The receipt
A47: Q046 | B47: My results have been lackluster. | C47: =IF(LEN(TRIM(B47))=0,0,LEN(TRIM(B47))-LEN(SUBSTITUTE(TRIM(B47)," ",""))+1) | D47: ProHealth NMN Pro (Uthever) | E47: Rick · 3★ · Sep 2021 | F47: Verbatim | G47: Grief | H47: Know whether it's working | I47: OBJECTION · Felt nothing | J47: Month 2+ | O47: Y | P47: =IF(C47<12,"Y","") | Q47: =COUNTIF(K47:P47,"Y") | R47: =IF(Q47>=3,"USE","CONTEXT") | S47: A1 You won't feel it
A48: Q047 | B48: I took Niagen brand of NR before trying NMN and I was noticing some cognitive benefit. | C48: =IF(LEN(TRIM(B48))=0,0,LEN(TRIM(B48))-LEN(SUBSTITUTE(TRIM(B48)," ",""))+1) | D48: ProHealth NMN Pro (Uthever) | E48: Rick · 3★ · Sep 2021 | F48: Verbatim | G48: Hope | H48: Think clearly again | I48: OBJECTION · NR worked better | J48: Comparing brands | L48: Y | M48: Y | P48: =IF(C48<12,"Y","") | Q48: =COUNTIF(K48:P48,"Y") | R48: =IF(Q48>=3,"USE","CONTEXT") | S48: A4 Dose is the product
A49: Q048 | B49: I take lots of supplements so maybe there was no deficiency that needed to be addressed. | C49: =IF(LEN(TRIM(B49))=0,0,LEN(TRIM(B49))-LEN(SUBSTITUTE(TRIM(B49)," ",""))+1) | D49: ProHealth NMN Pro (Uthever) | E49: Rick · 3★ · Sep 2021 | F49: Verbatim | G49: Shame | H49: Know whether it's working | I49: OBJECTION · Stack tax | J49: Month 2+ | N49: Y | O49: Y | P49: =IF(C49<12,"Y","") | Q49: =COUNTIF(K49:P49,"Y") | R49: =IF(Q49>=3,"USE","CONTEXT") | S49: A6 Retire the shelf
A50: Q049 | B50: I bought some more expensive third party tested NMN and again I notice very little difference. | C50: =IF(LEN(TRIM(B50))=0,0,LEN(TRIM(B50))-LEN(SUBSTITUTE(TRIM(B50)," ",""))+1) | D50: ProHealth NMN Pro (Uthever) | E50: Rick · 3★ · Sep 2021 | F50: Verbatim | G50: Grief | H50: Know whether it's working | I50: OBJECTION · Felt nothing | J50: Reorder decision | M50: Y | N50: Y | O50: Y | P50: =IF(C50<12,"Y","") | Q50: =COUNTIF(K50:P50,"Y") | R50: =IF(Q50>=3,"USE","CONTEXT") | S50: A1 You won't feel it
A51: Q050 | B51: I didn't feel much. | C51: =IF(LEN(TRIM(B51))=0,0,LEN(TRIM(B51))-LEN(SUBSTITUTE(TRIM(B51)," ",""))+1) | D51: ProHealth NMN Pro (Uthever) | E51: Rick · 3★ · Sep 2021 | F51: Verbatim | G51: Grief | H51: Get my energy back | I51: OBJECTION · Felt nothing | J51: Weeks 2–4 | L51: Y | O51: Y | P51: =IF(C51<12,"Y","") | Q51: =COUNTIF(K51:P51,"Y") | R51: =IF(Q51>=3,"USE","CONTEXT") | S51: A1 You won't feel it
A52: Q051 | B52: After hundreds of hours research on NMN and NR, I decided to buy this product. | C52: =IF(LEN(TRIM(B52))=0,0,LEN(TRIM(B52))-LEN(SUBSTITUTE(TRIM(B52)," ",""))+1) | D52: ProHealth NMN Pro (Uthever) | E52: Amazon Reviewer · 3★ · Nov 2022 | F52: Verbatim | G52: Pride | H52: Be the person who did the research | I52: BENEFIT · Self-image | J52: Pre-purchase research | P52: =IF(C52<12,"Y","") | Q52: =COUNTIF(K52:P52,"Y") | R52: =IF(Q52>=3,"USE","CONTEXT") | S52: A4 Dose is the product
A53: Q052 | B53: I do not feel energy boost or anything like that. | C53: =IF(LEN(TRIM(B53))=0,0,LEN(TRIM(B53))-LEN(SUBSTITUTE(TRIM(B53)," ",""))+1) | D53: ProHealth NMN Pro (Uthever) | E53: Amazon Reviewer · 3★ · Nov 2022 | F53: Verbatim | G53: Grief | H53: Get my energy back | I53: OBJECTION · Felt nothing | J53: Weeks 2–4 | L53: Y | O53: Y | P53: =IF(C53<12,"Y","") | Q53: =COUNTIF(K53:P53,"Y") | R53: =IF(Q53>=3,"USE","CONTEXT") | S53: A1 You won't feel it
A54: Q053 | B54: Calm but hard to focus and daydreaming. | C54: =IF(LEN(TRIM(B54))=0,0,LEN(TRIM(B54))-LEN(SUBSTITUTE(TRIM(B54)," ",""))+1) | D54: ProHealth NMN Pro (Uthever) | E54: Amazon Reviewer · 3★ · Nov 2022 | F54: Verbatim | G54: Fear | H54: Think clearly again | I54: OBJECTION · Paradox effect | J54: Week 1 | L54: Y | O54: Y | P54: =IF(C54<12,"Y","") | Q54: =COUNTIF(K54:P54,"Y") | R54: =IF(Q54>=3,"USE","CONTEXT") | S54: A5 Gentle start
A55: Q054 | B55: I have many vivid dreams with light headache when I wake up. | C55: =IF(LEN(TRIM(B55))=0,0,LEN(TRIM(B55))-LEN(SUBSTITUTE(TRIM(B55)," ",""))+1) | D55: ProHealth NMN Pro (Uthever) | E55: Amazon Reviewer · 3★ · Nov 2022 | F55: Verbatim | G55: Fear | H55: Sleep through the night | I55: OBJECTION · Side effect | J55: Week 1 | K55: Y | L55: Y | O55: Y | P55: =IF(C55<12,"Y","") | Q55: =COUNTIF(K55:P55,"Y") | R55: =IF(Q55>=3,"USE","CONTEXT") | S55: A5 Gentle start
A56: Q055 | B56: Not sure this product contains real NMN or something else in it. | C56: =IF(LEN(TRIM(B56))=0,0,LEN(TRIM(B56))-LEN(SUBSTITUTE(TRIM(B56)," ",""))+1) | D56: ProHealth NMN Pro (Uthever) | E56: Amazon Reviewer · 3★ · Nov 2022 | F56: Verbatim | G56: Fear | H56: Not get ripped off | I56: OBJECTION · Is it real? | J56: Weeks 2–4 | O56: Y | P56: =IF(C56<12,"Y","") | Q56: =COUNTIF(K56:P56,"Y") | R56: =IF(Q56>=3,"USE","CONTEXT") | S56: A2 The receipt
A57: Q056 | B57: Be careful. | C57: =IF(LEN(TRIM(B57))=0,0,LEN(TRIM(B57))-LEN(SUBSTITUTE(TRIM(B57)," ",""))+1) | D57: ProHealth NMN Pro (Uthever) | E57: Amazon Reviewer · 3★ · Nov 2022 | F57: Verbatim | G57: Fear | H57: Not get ripped off | I57: OBJECTION · Is it real? | J57: Warning others | O57: Y | P57: =IF(C57<12,"Y","") | Q57: =COUNTIF(K57:P57,"Y") | R57: =IF(Q57>=3,"USE","CONTEXT") | S57: A2 The receipt
A58: Q057 | B58: I've tried it for less than a month and I haven't felt anything special yet. | C58: =IF(LEN(TRIM(B58))=0,0,LEN(TRIM(B58))-LEN(SUBSTITUTE(TRIM(B58)," ",""))+1) | D58: ProHealth NMN Pro (Uthever) | E58: CHAN MENG CHIA · 4★ · Jul 2022 | F58: Verbatim | G58: Hope | H58: Know whether it's working | I58: OBJECTION · Felt nothing | J58: Weeks 2–4 | K58: Y | L58: Y | O58: Y | P58: =IF(C58<12,"Y","") | Q58: =COUNTIF(K58:P58,"Y") | R58: =IF(Q58>=3,"USE","CONTEXT") | S58: A1 You won't feel it
A59: Q058 | B59: I have used similar products before, I felt obviously the change in my body. | C59: =IF(LEN(TRIM(B59))=0,0,LEN(TRIM(B59))-LEN(SUBSTITUTE(TRIM(B59)," ",""))+1) | D59: ProHealth NMN Pro (Uthever) | E59: CHAN MENG CHIA · 4★ · Jul 2022 | F59: Verbatim | G59: Grief | H59: Get my energy back | I59: OBJECTION · Competitor worked | J59: Comparing brands | L59: Y | M59: Y | O59: Y | P59: =IF(C59<12,"Y","") | Q59: =COUNTIF(K59:P59,"Y") | R59: =IF(Q59>=3,"USE","CONTEXT") | S59: A1 You won't feel it
A60: Q059 | B60: In each bottle, I found several capsules that are broken. | C60: =IF(LEN(TRIM(B60))=0,0,LEN(TRIM(B60))-LEN(SUBSTITUTE(TRIM(B60)," ",""))+1) | D60: ProHealth NMN Pro (Uthever) | E60: Ms12587 · 1★ · Oct 2021 · Singapore | F60: Verbatim | G60: Anger | H60: Verify it's real and safe | I60: OBJECTION · Physical quality | J60: Unboxing / first inspection | L60: Y | O60: Y | P60: =IF(C60<12,"Y","") | Q60: =COUNTIF(K60:P60,"Y") | R60: =IF(Q60>=3,"USE","CONTEXT") | S60: A2 The receipt
A61: Q060 | B61: The broken capsules released the powder and all the other capsules tasted salty. | C61: =IF(LEN(TRIM(B61))=0,0,LEN(TRIM(B61))-LEN(SUBSTITUTE(TRIM(B61)," ",""))+1) | D61: ProHealth NMN Pro (Uthever) | E61: Ms12587 · 1★ · Oct 2021 · Singapore | F61: Verbatim | G61: Anger | H61: Verify it's real and safe | I61: OBJECTION · Physical quality | J61: First dose | L61: Y | O61: Y | P61: =IF(C61<12,"Y","") | Q61: =COUNTIF(K61:P61,"Y") | R61: =IF(Q61>=3,"USE","CONTEXT") | S61: A2 The receipt
A62: Q061 | B62: Some capsules are intact but empty or only half full. | C62: =IF(LEN(TRIM(B62))=0,0,LEN(TRIM(B62))-LEN(SUBSTITUTE(TRIM(B62)," ",""))+1) | D62: ProHealth NMN Pro (Uthever) | E62: Ms12587 · 1★ · Oct 2021 · Singapore | F62: Verbatim | G62: Anger | H62: Not get ripped off | I62: OBJECTION · Short-filled | J62: Unboxing / first inspection | L62: Y | O62: Y | P62: =IF(C62<12,"Y","") | Q62: =COUNTIF(K62:P62,"Y") | R62: =IF(Q62>=3,"USE","CONTEXT") | S62: A2 The receipt
A63: Q062 | B63: This has made me seriously wonder the overall quality of the product. | C63: =IF(LEN(TRIM(B63))=0,0,LEN(TRIM(B63))-LEN(SUBSTITUTE(TRIM(B63)," ",""))+1) | D63: ProHealth NMN Pro (Uthever) | E63: Ms12587 · 1★ · Oct 2021 · Singapore | F63: Verbatim | G63: Fear | H63: Verify it's real and safe | I63: OBJECTION · Trust collapse | J63: Unboxing / first inspection | O63: Y | P63: =IF(C63<12,"Y","") | Q63: =COUNTIF(K63:P63,"Y") | R63: =IF(Q63>=3,"USE","CONTEXT") | S63: A2 The receipt
A64: Q063 | B64: They claim high-standard QC. Based on what I see, this is not what they have claimed. | C64: =IF(LEN(TRIM(B64))=0,0,LEN(TRIM(B64))-LEN(SUBSTITUTE(TRIM(B64)," ",""))+1) | D64: ProHealth NMN Pro (Uthever) | E64: Ms12587 · 1★ · Oct 2021 · Singapore | F64: Verbatim | G64: Anger | H64: Not get ripped off | I64: OBJECTION · Claim vs reality | J64: Warning others | O64: Y | P64: =IF(C64<12,"Y","") | Q64: =COUNTIF(K64:P64,"Y") | R64: =IF(Q64>=3,"USE","CONTEXT") | S64: A2 The receipt
A65: Q064 | B65: The taste is so awful, smells like chemicals. | C65: =IF(LEN(TRIM(B65))=0,0,LEN(TRIM(B65))-LEN(SUBSTITUTE(TRIM(B65)," ",""))+1) | D65: ProHealth NMN Pro (Uthever) | E65: Tall Young · 1★ · Jul 2022 | F65: Verbatim | G65: Anger | H65: Protect a sensitive body | I65: OBJECTION · Smell / taste | J65: First dose | L65: Y | O65: Y | P65: =IF(C65<12,"Y","") | Q65: =COUNTIF(K65:P65,"Y") | R65: =IF(Q65>=3,"USE","CONTEXT") | S65: A5 Gentle start
A66: Q065 | B66: Gave me an allergic reaction. | C66: =IF(LEN(TRIM(B66))=0,0,LEN(TRIM(B66))-LEN(SUBSTITUTE(TRIM(B66)," ",""))+1) | D66: ProHealth NMN Pro (Uthever) | E66: Tall Young · 1★ · Jul 2022 | F66: Verbatim | G66: Fear | H66: Protect a sensitive body | I66: OBJECTION · Adverse reaction | J66: First dose | L66: Y | O66: Y | P66: =IF(C66<12,"Y","") | Q66: =COUNTIF(K66:P66,"Y") | R66: =IF(Q66>=3,"USE","CONTEXT") | S66: A5 Gentle start
A67: Q066 | B67: Cannot be returned. | C67: =IF(LEN(TRIM(B67))=0,0,LEN(TRIM(B67))-LEN(SUBSTITUTE(TRIM(B67)," ",""))+1) | D67: ProHealth NMN Pro (Uthever) | E67: Tall Young · 1★ · Jul 2022 | F67: Verbatim | G67: Anger | H67: Not get ripped off | I67: OBJECTION · No refund | J67: Abandonment / refund | O67: Y | P67: =IF(C67<12,"Y","") | Q67: =COUNTIF(K67:P67,"Y") | R67: =IF(Q67>=3,"USE","CONTEXT") | S67: A3 Do the math
A68: Q067 | B68: Do not purchase this product. | C68: =IF(LEN(TRIM(B68))=0,0,LEN(TRIM(B68))-LEN(SUBSTITUTE(TRIM(B68)," ",""))+1) | D68: ProHealth NMN Pro (Uthever) | E68: Tall Young · 1★ · Jul 2022 | F68: Verbatim | G68: Anger | H68: Not get ripped off | I68: OBJECTION · Trust collapse | J68: Warning others | O68: Y | P68: =IF(C68<12,"Y","") | Q68: =COUNTIF(K68:P68,"Y") | R68: =IF(Q68>=3,"USE","CONTEXT") | S68: A2 The receipt
A69: Q068 | B69: I've become more interested in healthy aging and longevity as I get older. | C69: =IF(LEN(TRIM(B69))=0,0,LEN(TRIM(B69))-LEN(SUBSTITUTE(TRIM(B69)," ",""))+1) | D69: ProHealth NMN Pro (Uthever) | E69: Vine reviewer · 4★ · Jun 2026 | F69: Verbatim | G69: Fear | H69: Stay functional as I age | I69: BENEFIT · Identity fit | J69: Pre-purchase research | M69: Y | O69: Y | P69: =IF(C69<12,"Y","") | Q69: =COUNTIF(K69:P69,"Y") | R69: =IF(Q69>=3,"USE","CONTEXT") | S69: A6 Retire the shelf
A70: Q069 | B70: My energy levels have been a little more consistent and I seem to have better stamina. | C70: =IF(LEN(TRIM(B70))=0,0,LEN(TRIM(B70))-LEN(SUBSTITUTE(TRIM(B70)," ",""))+1) | D70: ProHealth NMN Pro (Uthever) | E70: Vine reviewer · 4★ · Jun 2026 | F70: Verbatim | G70: Relief | H70: Get my energy back | I70: BENEFIT · Subtle energy | J70: Weeks 2–4 | L70: Y | M70: Y | O70: Y | P70: =IF(C70<12,"Y","") | Q70: =COUNTIF(K70:P70,"Y") | R70: =IF(Q70>=3,"USE","CONTEXT") | S70: A1 You won't feel it
A71: Q070 | B71: The bottle contains as little as a 15-day supply. | C71: =IF(LEN(TRIM(B71))=0,0,LEN(TRIM(B71))-LEN(SUBSTITUTE(TRIM(B71)," ",""))+1) | D71: ProHealth NMN Pro (Uthever) | E71: Vine reviewer · 4★ · Jun 2026 | F71: Verbatim | G71: Anger | H71: Justify the ongoing spend | I71: OBJECTION · True supply length | J71: Doing the price math | O71: Y | P71: =IF(C71<12,"Y","") | Q71: =COUNTIF(K71:P71,"Y") | R71: =IF(Q71>=3,"USE","CONTEXT") | S71: A3 Do the math
A72: Q071 | B72: The bottle felt and looked practically empty when I first opened it. | C72: =IF(LEN(TRIM(B72))=0,0,LEN(TRIM(B72))-LEN(SUBSTITUTE(TRIM(B72)," ",""))+1) | D72: ProHealth NMN Pro (Uthever) | E72: Vine reviewer · 4★ · Jun 2026 | F72: Verbatim | G72: Anger | H72: Not get ripped off | I72: OBJECTION · Fill level | J72: Unboxing / first inspection | L72: Y | O72: Y | P72: =IF(C72<12,"Y","") | Q72: =COUNTIF(K72:P72,"Y") | R72: =IF(Q72>=3,"USE","CONTEXT") | S72: A3 Do the math
A73: Q072 | B73: There were 30 capsules. I counted them to be sure. | C73: =IF(LEN(TRIM(B73))=0,0,LEN(TRIM(B73))-LEN(SUBSTITUTE(TRIM(B73)," ",""))+1) | D73: ProHealth NMN Pro (Uthever) | E73: Vine reviewer · 4★ · Jun 2026 | F73: Verbatim | G73: Fear | H73: Not get ripped off | I73: OBJECTION · Fill level | J73: Unboxing / first inspection | N73: Y | O73: Y | P73: =IF(C73<12,"Y","") | Q73: =COUNTIF(K73:P73,"Y") | R73: =IF(Q73>=3,"USE","CONTEXT") | S73: A3 Do the math
A74: Q073 | B74: This product can get expensive if you plan to take it long term. | C74: =IF(LEN(TRIM(B74))=0,0,LEN(TRIM(B74))-LEN(SUBSTITUTE(TRIM(B74)," ",""))+1) | D74: ProHealth NMN Pro (Uthever) | E74: Vine reviewer · 4★ · Jun 2026 | F74: Verbatim | G74: Fear | H74: Justify the ongoing spend | I74: OBJECTION · Cost per day | J74: Reorder decision | O74: Y | P74: =IF(C74<12,"Y","") | Q74: =COUNTIF(K74:P74,"Y") | R74: =IF(Q74>=3,"USE","CONTEXT") | S74: A3 Do the math
A75: Q074 | B75: I haven't experienced any side effects, stomach upset, or other issues. | C75: =IF(LEN(TRIM(B75))=0,0,LEN(TRIM(B75))-LEN(SUBSTITUTE(TRIM(B75)," ",""))+1) | D75: ProHealth NMN Pro (Uthever) | E75: Vine reviewer · 4★ · Jun 2026 | F75: Verbatim | G75: Relief | H75: Protect a sensitive body | I75: BENEFIT · Tolerability | J75: Weeks 2–4 | L75: Y | O75: Y | P75: =IF(C75<12,"Y","") | Q75: =COUNTIF(K75:P75,"Y") | R75: =IF(Q75>=3,"USE","CONTEXT") | S75: A5 Gentle start
A76: Q075 | B76: Aging gracefully, which I am hoping to do. | C76: =IF(LEN(TRIM(B76))=0,0,LEN(TRIM(B76))-LEN(SUBSTITUTE(TRIM(B76)," ",""))+1) | D76: ProHealth NMN Pro (Uthever) | E76: Vine reviewer · 4★ · Jun 2026 | F76: Verbatim | G76: Hope | H76: Slow visible aging | I76: BENEFIT · Identity fit | J76: Pre-purchase research | N76: Y | O76: Y | P76: =IF(C76<12,"Y","") | Q76: =COUNTIF(K76:P76,"Y") | R76: =IF(Q76>=3,"USE","CONTEXT") | S76: A6 Retire the shelf
A77: Q076 | B77: Be patient. | C77: =IF(LEN(TRIM(B77))=0,0,LEN(TRIM(B77))-LEN(SUBSTITUTE(TRIM(B77)," ",""))+1) | D77: ProHealth NMN Pro (Uthever) | E77: Kyle · 4★ · Jun 2026 · Vine | F77: Verbatim | G77: Hope | H77: Know whether it's working | I77: BENEFIT · Realistic timeline | J77: Week 1 | O77: Y | P77: =IF(C77<12,"Y","") | Q77: =COUNTIF(K77:P77,"Y") | R77: =IF(Q77>=3,"USE","CONTEXT") | S77: A1 You won't feel it
A78: Q077 | B78: It takes a little longer to take effect since your body needs to digest them first. | C78: =IF(LEN(TRIM(B78))=0,0,LEN(TRIM(B78))-LEN(SUBSTITUTE(TRIM(B78)," ",""))+1) | D78: ProHealth NMN Pro (Uthever) | E78: Kyle · 4★ · Jun 2026 · Vine | F78: Verbatim | G78: Hope | H78: Know whether it's working | I78: OBJECTION · Timeline unclear | J78: Week 1 | L78: Y | O78: Y | P78: =IF(C78<12,"Y","") | Q78: =COUNTIF(K78:P78,"Y") | R78: =IF(Q78>=3,"USE","CONTEXT") | S78: A1 You won't feel it
A79: Q078 | B79: The capsules aren't too large nor do they have any unpleasant taste or scent. | C79: =IF(LEN(TRIM(B79))=0,0,LEN(TRIM(B79))-LEN(SUBSTITUTE(TRIM(B79)," ",""))+1) | D79: ProHealth NMN Pro (Uthever) | E79: Kyle · 4★ · Jun 2026 · Vine | F79: Verbatim | G79: Relief | H79: Protect a sensitive body | I79: BENEFIT · Sensory ease | J79: First dose | L79: Y | O79: Y | P79: =IF(C79<12,"Y","") | Q79: =COUNTIF(K79:P79,"Y") | R79: =IF(Q79>=3,"USE","CONTEXT") | S79: A5 Gentle start
A80: Q079 | B80: A really nice boost of energy, and it's sustained, so no crash later in the day. | C80: =IF(LEN(TRIM(B80))=0,0,LEN(TRIM(B80))-LEN(SUBSTITUTE(TRIM(B80)," ",""))+1) | D80: ProHealth NMN Pro (Uthever) | E80: Kyle · 4★ · Jun 2026 · Vine | F80: Verbatim | G80: Relief | H80: Get my energy back | I80: BENEFIT · Clean energy | J80: Weeks 2–4 | K80: Y | L80: Y | O80: Y | P80: =IF(C80<12,"Y","") | Q80: =COUNTIF(K80:P80,"Y") | R80: =IF(Q80>=3,"USE","CONTEXT") | S80: A1 You won't feel it
A81: Q080 | B81: I read where people kept saying they did not get a spoon but mine was in the bag. | C81: =IF(LEN(TRIM(B81))=0,0,LEN(TRIM(B81))-LEN(SUBSTITUTE(TRIM(B81)," ",""))+1) | D81: ProHealth NMN Powder | E81: Jackie Waldrop · 4★ · Jan 2023 | F81: Verbatim | G81: Relief | H81: Not get ripped off | I81: BENEFIT · Fear resolved | J81: Unboxing / first inspection | O81: Y | P81: =IF(C81<12,"Y","") | Q81: =COUNTIF(K81:P81,"Y") | R81: =IF(Q81>=3,"USE","CONTEXT") | S81: A2 The receipt
A82: Q081 | B82: The taste is kind of twangy. Not bad. | C82: =IF(LEN(TRIM(B82))=0,0,LEN(TRIM(B82))-LEN(SUBSTITUTE(TRIM(B82)," ",""))+1) | D82: ProHealth NMN Powder | E82: Jackie Waldrop · 4★ · Jan 2023 | F82: Verbatim | G82: Relief | H82: Protect a sensitive body | I82: BENEFIT · Taste acceptable | J82: First dose | L82: Y | O82: Y | P82: =IF(C82<12,"Y","") | Q82: =COUNTIF(K82:P82,"Y") | R82: =IF(Q82>=3,"USE","CONTEXT") | S82: A5 Gentle start
A83: Q082 | B83: It disappears in the water with no cloud and is clear, easy to drink. | C83: =IF(LEN(TRIM(B83))=0,0,LEN(TRIM(B83))-LEN(SUBSTITUTE(TRIM(B83)," ",""))+1) | D83: ProHealth NMN Powder | E83: Jackie Waldrop · 4★ · Jan 2023 | F83: Verbatim | G83: Relief | H83: Protect a sensitive body | I83: BENEFIT · Dissolves clean | J83: First dose | L83: Y | O83: Y | P83: =IF(C83<12,"Y","") | Q83: =COUNTIF(K83:P83,"Y") | R83: =IF(Q83>=3,"USE","CONTEXT") | S83: A5 Gentle start
A84: Q083 | B84: My husband thought I gave him just a glass of water. | C84: =IF(LEN(TRIM(B84))=0,0,LEN(TRIM(B84))-LEN(SUBSTITUTE(TRIM(B84)," ",""))+1) | D84: ProHealth NMN Powder | E84: Jackie Waldrop · 4★ · Jan 2023 | F84: Verbatim | G84: Relief | H84: Care for my spouse | I84: BENEFIT · Dissolves clean | J84: First dose | L84: Y | O84: Y | P84: =IF(C84<12,"Y","") | Q84: =COUNTIF(K84:P84,"Y") | R84: =IF(Q84>=3,"USE","CONTEXT") | S84: A5 Gentle start
A85: Q084 | B85: He has COPD and I have IBS. Wanted to try it for those two things. | C85: =IF(LEN(TRIM(B85))=0,0,LEN(TRIM(B85))-LEN(SUBSTITUTE(TRIM(B85)," ",""))+1) | D85: ProHealth NMN Powder | E85: Jackie Waldrop · 4★ · Jan 2023 | F85: Verbatim | G85: Hope | H85: Care for my spouse | I85: OBJECTION · Disease hope [DO NOT USE] | J85: Pre-purchase research | L85: Y | O85: Y | P85: =IF(C85<12,"Y","") | Q85: =COUNTIF(K85:P85,"Y") | R85: =IF(Q85>=3,"USE","CONTEXT") | S85: §07 Guardrail — do not use
A86: Q085 | B86: I had a bad reaction the first day and had cramps in my stomach. | C86: =IF(LEN(TRIM(B86))=0,0,LEN(TRIM(B86))-LEN(SUBSTITUTE(TRIM(B86)," ",""))+1) | D86: ProHealth NMN Powder | E86: Jackie Waldrop · 4★ · Jan 2023 | F86: Verbatim | G86: Fear | H86: Protect a sensitive body | I86: OBJECTION · Gut reaction | J86: First dose | K86: Y | L86: Y | O86: Y | P86: =IF(C86<12,"Y","") | Q86: =COUNTIF(K86:P86,"Y") | R86: =IF(Q86>=3,"USE","CONTEXT") | S86: A5 Gentle start
A87: Q086 | B87: I was afraid to try it again. | C87: =IF(LEN(TRIM(B87))=0,0,LEN(TRIM(B87))-LEN(SUBSTITUTE(TRIM(B87)," ",""))+1) | D87: ProHealth NMN Powder | E87: Jackie Waldrop · 4★ · Jan 2023 | F87: Verbatim | G87: Fear | H87: Protect a sensitive body | I87: OBJECTION · Gut reaction | J87: Week 1 | L87: Y | N87: Y | O87: Y | P87: =IF(C87<12,"Y","") | Q87: =COUNTIF(K87:P87,"Y") | R87: =IF(Q87>=3,"USE","CONTEXT") | S87: A5 Gentle start
A88: Q087 | B88: By the third day he said I think it is helping me, so I started back taking it. | C88: =IF(LEN(TRIM(B88))=0,0,LEN(TRIM(B88))-LEN(SUBSTITUTE(TRIM(B88)," ",""))+1) | D88: ProHealth NMN Powder | E88: Jackie Waldrop · 4★ · Jan 2023 | F88: Verbatim | G88: Hope | H88: Care for my spouse | I88: BENEFIT · Push through week 1 | J88: Week 1 | K88: Y | O88: Y | P88: =IF(C88<12,"Y","") | Q88: =COUNTIF(K88:P88,"Y") | R88: =IF(Q88>=3,"USE","CONTEXT") | S88: A5 Gentle start
A89: Q088 | B89: Keeping a log of our vitals. | C89: =IF(LEN(TRIM(B89))=0,0,LEN(TRIM(B89))-LEN(SUBSTITUTE(TRIM(B89)," ",""))+1) | D89: ProHealth NMN Powder | E89: Jackie Waldrop · 4★ · Jan 2023 | F89: Verbatim | G89: Hope | H89: Know whether it's working | I89: BENEFIT · Wants a scoreboard | J89: Week 1 | O89: Y | P89: =IF(C89<12,"Y","") | Q89: =COUNTIF(K89:P89,"Y") | R89: =IF(Q89>=3,"USE","CONTEXT") | S89: A1 You won't feel it
A90: Q089 | B90: Hoping that soon he won't have to take them any more and just the NMN. | C90: =IF(LEN(TRIM(B90))=0,0,LEN(TRIM(B90))-LEN(SUBSTITUTE(TRIM(B90)," ",""))+1) | D90: ProHealth NMN Powder | E90: Jackie Waldrop · 4★ · Jan 2023 | F90: Verbatim | G90: Hope | H90: Care for my spouse | I90: OBJECTION · Drug replacement [DO NOT USE] | J90: Month 2+ | O90: Y | P90: =IF(C90<12,"Y","") | Q90: =COUNTIF(K90:P90,"Y") | R90: =IF(Q90>=3,"USE","CONTEXT") | S90: §07 Guardrail — do not use
A91: Q090 | B91: NAD+ as a molecule is too large to be effectively absorbed through the digestive system. | C91: =IF(LEN(TRIM(B91))=0,0,LEN(TRIM(B91))-LEN(SUBSTITUTE(TRIM(B91)," ",""))+1) | D91: Nutricost NAD+ 1,000mg | E91: Listing summary | F91: Paraphrase — not quotable | G91: Fear | H91: Verify it's real and safe | I91: OBJECTION · Bioavailability | J91: Pre-purchase research | P91: =IF(C91<12,"Y","") | Q91: =COUNTIF(K91:P91,"Y") | R91: =IF(Q91>=3,"USE","CONTEXT") | S91: A4 Dose is the product
A92: Q091 | B92: Precursors like NMN or NR may be more effective for raising NAD+ levels. | C92: =IF(LEN(TRIM(B92))=0,0,LEN(TRIM(B92))-LEN(SUBSTITUTE(TRIM(B92)," ",""))+1) | D92: Nutricost NAD+ 1,000mg | E92: Listing summary | F92: Paraphrase — not quotable | G92: Hope | H92: Be the person who did the research | I92: BENEFIT · NMN over NAD+ | J92: Comparing brands | P92: =IF(C92<12,"Y","") | Q92: =COUNTIF(K92:P92,"Y") | R92: =IF(Q92>=3,"USE","CONTEXT") | S92: A4 Dose is the product
A93: Q092 | B93: Too strong. | C93: =IF(LEN(TRIM(B93))=0,0,LEN(TRIM(B93))-LEN(SUBSTITUTE(TRIM(B93)," ",""))+1) | D93: Nutricost NAD+ 1,000mg | E93: Listing summary | F93: Quoted fragment | G93: Fear | H93: Protect a sensitive body | I93: OBJECTION · Over-stimulation | J93: First dose | L93: Y | O93: Y | P93: =IF(C93<12,"Y","") | Q93: =COUNTIF(K93:P93,"Y") | R93: =IF(Q93>=3,"USE","CONTEXT") | S93: A5 Gentle start
A94: Q093 | B94: Start with just 1 capsule to assess tolerance. | C94: =IF(LEN(TRIM(B94))=0,0,LEN(TRIM(B94))-LEN(SUBSTITUTE(TRIM(B94)," ",""))+1) | D94: Nutricost NAD+ 1,000mg | E94: Listing summary | F94: Paraphrase — not quotable | G94: Fear | H94: Protect a sensitive body | I94: BENEFIT · Self-invented protocol | J94: First dose | O94: Y | P94: =IF(C94<12,"Y","") | Q94: =COUNTIF(K94:P94,"Y") | R94: =IF(Q94>=3,"USE","CONTEXT") | S94: A5 Gentle start
A95: Q094 | B95: Does 1,000mg per serving exceed safe daily intake guidelines? | C95: =IF(LEN(TRIM(B95))=0,0,LEN(TRIM(B95))-LEN(SUBSTITUTE(TRIM(B95)," ",""))+1) | D95: Nutricost NAD+ 1,000mg | E95: Listing summary | F95: Paraphrase — not quotable | G95: Fear | H95: Verify it's real and safe | I95: OBJECTION · Dose too high | J95: Reading the label | O95: Y | P95: =IF(C95<12,"Y","") | Q95: =COUNTIF(K95:P95,"Y") | R95: =IF(Q95>=3,"USE","CONTEXT") | S95: A4 Dose is the product
A96: Q095 | B96: Should dosing be adjusted based on body weight? | C96: =IF(LEN(TRIM(B96))=0,0,LEN(TRIM(B96))-LEN(SUBSTITUTE(TRIM(B96)," ",""))+1) | D96: Nutricost NAD+ 1,000mg | E96: Listing summary | F96: Paraphrase — not quotable | G96: Fear | H96: Verify it's real and safe | I96: OBJECTION · Dose guidance | J96: Reading the label | O96: Y | P96: =IF(C96<12,"Y","") | Q96: =COUNTIF(K96:P96,"Y") | R96: =IF(Q96>=3,"USE","CONTEXT") | S96: A4 Dose is the product
A97: Q096 | B97: Stomach aches, cramping, and in some cases vomiting. | C97: =IF(LEN(TRIM(B97))=0,0,LEN(TRIM(B97))-LEN(SUBSTITUTE(TRIM(B97)," ",""))+1) | D97: Nutricost NAD+ 1,000mg | E97: Listing summary | F97: Paraphrase — not quotable | G97: Fear | H97: Protect a sensitive body | I97: OBJECTION · Gut reaction | J97: Week 1 | L97: Y | O97: Y | P97: =IF(C97<12,"Y","") | Q97: =COUNTIF(K97:P97,"Y") | R97: =IF(Q97>=3,"USE","CONTEXT") | S97: A5 Gentle start
A98: Q097 | B98: Rancid. | C98: =IF(LEN(TRIM(B98))=0,0,LEN(TRIM(B98))-LEN(SUBSTITUTE(TRIM(B98)," ",""))+1) | D98: Nutricost NMN 500mg | E98: Listing summary | F98: Quoted fragment | G98: Anger | H98: Protect a sensitive body | I98: OBJECTION · Smell | J98: Unboxing / first inspection | L98: Y | O98: Y | P98: =IF(C98<12,"Y","") | Q98: =COUNTIF(K98:P98,"Y") | R98: =IF(Q98>=3,"USE","CONTEXT") | S98: A5 Gentle start
A99: Q098 | B99: Smells like interior paint. | C99: =IF(LEN(TRIM(B99))=0,0,LEN(TRIM(B99))-LEN(SUBSTITUTE(TRIM(B99)," ",""))+1) | D99: Nutricost NMN 500mg | E99: Listing summary | F99: Quoted fragment | G99: Anger | H99: Protect a sensitive body | I99: OBJECTION · Smell | J99: Unboxing / first inspection | L99: Y | O99: Y | P99: =IF(C99<12,"Y","") | Q99: =COUNTIF(K99:P99,"Y") | R99: =IF(Q99>=3,"USE","CONTEXT") | S99: A5 Gentle start
A100: Q099 | B100: Did not feel any changes. | C100: =IF(LEN(TRIM(B100))=0,0,LEN(TRIM(B100))-LEN(SUBSTITUTE(TRIM(B100)," ",""))+1) | D100: Nutricost NMN 500mg | E100: Listing summary | F100: Quoted fragment | G100: Grief | H100: Know whether it's working | I100: OBJECTION · Felt nothing | J100: Weeks 2–4 | L100: Y | O100: Y | P100: =IF(C100<12,"Y","") | Q100: =COUNTIF(K100:P100,"Y") | R100: =IF(Q100>=3,"USE","CONTEXT") | S100: A1 You won't feel it
...

Sheet Rollups
A1: Where the emotional weight sits
A2: All counts are live formulas over the Quote Bank sheet.
A4: By emotion
A5: Emotion | B5: Quotes | C5: Usable (score 3+)
A6: Fear | B6: =COUNTIF('Quote Bank'!$G$2:$G$190,A6) | C6: =COUNTIFS('Quote Bank'!$G$2:$G$190,A6,'Quote Bank'!$R$2:$R$190,"USE")
A7: Shame | B7: =COUNTIF('Quote Bank'!$G$2:$G$190,A7) | C7: =COUNTIFS('Quote Bank'!$G$2:$G$190,A7,'Quote Bank'!$R$2:$R$190,"USE")
A8: Hope | B8: =COUNTIF('Quote Bank'!$G$2:$G$190,A8) | C8: =COUNTIFS('Quote Bank'!$G$2:$G$190,A8,'Quote Bank'!$R$2:$R$190,"USE")
A9: Relief | B9: =COUNTIF('Quote Bank'!$G$2:$G$190,A9) | C9: =COUNTIFS('Quote Bank'!$G$2:$G$190,A9,'Quote Bank'!$R$2:$R$190,"USE")
A10: Pride | B10: =COUNTIF('Quote Bank'!$G$2:$G$190,A10) | C10: =COUNTIFS('Quote Bank'!$G$2:$G$190,A10,'Quote Bank'!$R$2:$R$190,"USE")
A11: Anger | B11: =COUNTIF('Quote Bank'!$G$2:$G$190,A11) | C11: =COUNTIFS('Quote Bank'!$G$2:$G$190,A11,'Quote Bank'!$R$2:$R$190,"USE")
A12: Grief | B12: =COUNTIF('Quote Bank'!$G$2:$G$190,A12) | C12: =COUNTIFS('Quote Bank'!$G$2:$G$190,A12,'Quote Bank'!$R$2:$R$190,"USE")
A15: By job to be done
A16: Job to be done | B16: Quotes | C16: Usable (score 3+)
A17: Be the person who did the research | B17: =COUNTIF('Quote Bank'!$H$2:$H$190,A17) | C17: =COUNTIFS('Quote Bank'!$H$2:$H$190,A17,'Quote Bank'!$R$2:$R$190,"USE")
A18: Care for my spouse | B18: =COUNTIF('Quote Bank'!$H$2:$H$190,A18) | C18: =COUNTIFS('Quote Bank'!$H$2:$H$190,A18,'Quote Bank'!$R$2:$R$190,"USE")
A19: Get my energy back | B19: =COUNTIF('Quote Bank'!$H$2:$H$190,A19) | C19: =COUNTIFS('Quote Bank'!$H$2:$H$190,A19,'Quote Bank'!$R$2:$R$190,"USE")
A20: Justify the ongoing spend | B20: =COUNTIF('Quote Bank'!$H$2:$H$190,A20) | C20: =COUNTIFS('Quote Bank'!$H$2:$H$190,A20,'Quote Bank'!$R$2:$R$190,"USE")
A21: Know whether it's working | B21: =COUNTIF('Quote Bank'!$H$2:$H$190,A21) | C21: =COUNTIFS('Quote Bank'!$H$2:$H$190,A21,'Quote Bank'!$R$2:$R$190,"USE")
A22: Not get ripped off | B22: =COUNTIF('Quote Bank'!$H$2:$H$190,A22) | C22: =COUNTIFS('Quote Bank'!$H$2:$H$190,A22,'Quote Bank'!$R$2:$R$190,"USE")
A23: Protect a sensitive body | B23: =COUNTIF('Quote Bank'!$H$2:$H$190,A23) | C23: =COUNTIFS('Quote Bank'!$H$2:$H$190,A23,'Quote Bank'!$R$2:$R$190,"USE")
A24: Simplify my routine | B24: =COUNTIF('Quote Bank'!$H$2:$H$190,A24) | C24: =COUNTIFS('Quote Bank'!$H$2:$H$190,A24,'Quote Bank'!$R$2:$R$190,"USE")
A25: Sleep through the night | B25: =COUNTIF('Quote Bank'!$H$2:$H$190,A25) | C25: =COUNTIFS('Quote Bank'!$H$2:$H$190,A25,'Quote Bank'!$R$2:$R$190,"USE")
A26: Slow visible aging | B26: =COUNTIF('Quote Bank'!$H$2:$H$190,A26) | C26: =COUNTIFS('Quote Bank'!$H$2:$H$190,A26,'Quote Bank'!$R$2:$R$190,"USE")
A27: Stay functional as I age | B27: =COUNTIF('Quote Bank'!$H$2:$H$190,A27) | C27: =COUNTIFS('Quote Bank'!$H$2:$H$190,A27,'Quote Bank'!$R$2:$R$190,"USE")
A28: Think clearly again | B28: =COUNTIF('Quote Bank'!$H$2:$H$190,A28) | C28: =COUNTIFS('Quote Bank'!$H$2:$H$190,A28,'Quote Bank'!$R$2:$R$190,"USE")
A29: Verify it's real and safe | B29: =COUNTIF('Quote Bank'!$H$2:$H$190,A29) | C29: =COUNTIFS('Quote Bank'!$H$2:$H$190,A29,'Quote Bank'!$R$2:$R$190,"USE")
A32: By trigger moment
A33: Trigger moment | B33: Quotes | C33: Usable (score 3+)
A34: Pre-purchase research | B34: =COUNTIF('Quote Bank'!$J$2:$J$190,A34) | C34: =COUNTIFS('Quote Bank'!$J$2:$J$190,A34,'Quote Bank'!$R$2:$R$190,"USE")
A35: Comparing brands | B35: =COUNTIF('Quote Bank'!$J$2:$J$190,A35) | C35: =COUNTIFS('Quote Bank'!$J$2:$J$190,A35,'Quote Bank'!$R$2:$R$190,"USE")
A36: Reading the label | B36: =COUNTIF('Quote Bank'!$J$2:$J$190,A36) | C36: =COUNTIFS('Quote Bank'!$J$2:$J$190,A36,'Quote Bank'!$R$2:$R$190,"USE")
A37: Doing the price math | B37: =COUNTIF('Quote Bank'!$J$2:$J$190,A37) | C37: =COUNTIFS('Quote Bank'!$J$2:$J$190,A37,'Quote Bank'!$R$2:$R$190,"USE")
A38: Unboxing / first inspection | B38: =COUNTIF('Quote Bank'!$J$2:$J$190,A38) | C38: =COUNTIFS('Quote Bank'!$J$2:$J$190,A38,'Quote Bank'!$R$2:$R$190,"USE")
A39: First dose | B39: =COUNTIF('Quote Bank'!$J$2:$J$190,A39) | C39: =COUNTIFS('Quote Bank'!$J$2:$J$190,A39,'Quote Bank'!$R$2:$R$190,"USE")
A40: Week 1 | B40: =COUNTIF('Quote Bank'!$J$2:$J$190,A40) | C40: =COUNTIFS('Quote Bank'!$J$2:$J$190,A40,'Quote Bank'!$R$2:$R$190,"USE")
A41: Weeks 2–4 | B41: =COUNTIF('Quote Bank'!$J$2:$J$190,A41) | C41: =COUNTIFS('Quote Bank'!$J$2:$J$190,A41,'Quote Bank'!$R$2:$R$190,"USE")
A42: Month 2+ | B42: =COUNTIF('Quote Bank'!$J$2:$J$190,A42) | C42: =COUNTIFS('Quote Bank'!$J$2:$J$190,A42,'Quote Bank'!$R$2:$R$190,"USE")
A43: Reorder decision | B43: =COUNTIF('Quote Bank'!$J$2:$J$190,A43) | C43: =COUNTIFS('Quote Bank'!$J$2:$J$190,A43,'Quote Bank'!$R$2:$R$190,"USE")
A44: Abandonment / refund | B44: =COUNTIF('Quote Bank'!$J$2:$J$190,A44) | C44: =COUNTIFS('Quote Bank'!$J$2:$J$190,A44,'Quote Bank'!$R$2:$R$190,"USE")
A45: Warning others | B45: =COUNTIF('Quote Bank'!$J$2:$J$190,A45) | C45: =COUNTIFS('Quote Bank'!$J$2:$J$190,A45,'Quote Bank'!$R$2:$R$190,"USE")
A48: By angle (maps to the teardown)
A49: Angle | B49: Quotes | C49: Usable (score 3+)
A50: A1 You won't feel it | B50: =COUNTIF('Quote Bank'!$S$2:$S$190,A50) | C50: =COUNTIFS('Quote Bank'!$S$2:$S$190,A50,'Quote Bank'!$R$2:$R$190,"USE")
A51: A2 The receipt | B51: =COUNTIF('Quote Bank'!$S$2:$S$190,A51) | C51: =COUNTIFS('Quote Bank'!$S$2:$S$190,A51,'Quote Bank'!$R$2:$R$190,"USE")
A52: A3 Do the math | B52: =COUNTIF('Quote Bank'!$S$2:$S$190,A52) | C52: =COUNTIFS('Quote Bank'!$S$2:$S$190,A52,'Quote Bank'!$R$2:$R$190,"USE")
A53: A4 Dose is the product | B53: =COUNTIF('Quote Bank'!$S$2:$S$190,A53) | C53: =COUNTIFS('Quote Bank'!$S$2:$S$190,A53,'Quote Bank'!$R$2:$R$190,"USE")
A54: A5 Gentle start | B54: =COUNTIF('Quote Bank'!$S$2:$S$190,A54) | C54: =COUNTIFS('Quote Bank'!$S$2:$S$190,A54,'Quote Bank'!$R$2:$R$190,"USE")
A55: A6 Retire the shelf | B55: =COUNTIF('Quote Bank'!$S$2:$S$190,A55) | C55: =COUNTIFS('Quote Bank'!$S$2:$S$190,A55,'Quote Bank'!$R$2:$R$190,"USE")
A56: A7 Honest science | B56: =COUNTIF('Quote Bank'!$S$2:$S$190,A56) | C56: =COUNTIFS('Quote Bank'!$S$2:$S$190,A56,'Quote Bank'!$R$2:$R$190,"USE")
A57: §07 Guardrail — do not use | B57: =COUNTIF('Quote Bank'!$S$2:$S$190,A57) | C57: =COUNTIFS('Quote Bank'!$S$2:$S$190,A57,'Quote Bank'!$R$2:$R$190,"USE")

Sheet How to use this
A1: Voice-of-Customer Bank — how to use it
A3: One quote per row. Tagged so you can filter down to the exact line you need, then write copy that is transcription rather than invention.
A5: The six markers
A6: A quote earns a marker for each of these it contains. Column Q sums them; column R turns that into a verdict.
A8: • Time/place — names a specific hour, day, age or setting. "I took two pills around 8am."
A9: • Physical — a bodily sensation, not an abstraction. "Stomach gurgling loud enough that my coworkers noticed."
A10: • Former self — measures now against a previous version of themselves. "At 65 I needed more energy, not less."
A11: • Admission — something slightly embarrassing to say out loud. "I counted them to be sure."
A12: • Plain — everyday unbranded speech, no jargon, no ingredient names.
A13: • <12 words — computed live from the word count in column C.
A14: The verdict rule
A15: 3 or more markers = USE. These are the lines that can carry an ad, a subject line, or a headline more or less as written. Under 3 = CONTEXT: true and useful for understanding the buyer, but too abstract to run as copy. Roughly a third of the bank clears the bar, which is normal — you are looking for the few dozen lines that sound like a person, not a category.
... A27: The underlying document mixes about ten full verbatim reviews with AI-generated summaries of competitor listings. Percentages quoted in those summaries are directional, not measured. Treat this bank as a language and hypothesis source, then re-run the same tagging on your own reviews, support tickets and refund reasons — that is where the Prime-specific version lives.
